{
    "0": [
        "Amsterdam",
        4.51,
        52.2
    ],
    "1": [
        "Athens",
        23.42,
        37.58
    ],
    "2": [
        "Barcelona",
        2.07,
        41.22
    ],
    "3": [
        "Belgrade",
        20.25,
        44.47
    ],
    "4": [
        "Berlin",
        13.21,
        52.31
    ],
    "5": [
        "Bordeaux",
        -0.35,
        44.51
    ],
    "6": [
        "Brussels",
        4.2,
        50.49
    ],
    "7": [
        "Budapest",
        19.02,
        47.29
    ],
    "8": [
        "Copenhagen",
        12.32,
        55.41
    ],
    "9": [
        "Dublin",
        -6.15,
        53.21
    ],
    "10": [
        "Frankfurt",
        8.38,
        50.07
    ],
    "11": [
        "Glasgow",
        -4.16,
        55.51
    ],
    "12": [
        "Hamburg",
        10.0,
        53.33
    ],
    "13": [
        "London",
        -0.07,
        51.3
    ],
    "14": [
        "Lyon",
        4.49,
        45.43
    ],
    "15": [
        "Madrid",
        -3.42,
        40.25
    ],
    "16": [
        "Milan",
        9.11,
        45.28
    ],
    "17": [
        "Munich",
        11.33,
        48.07
    ],
    "18": [
        "Oslo",
        10.45,
        59.54
    ],
    "19": [
        "Paris",
        2.2,
        48.51
    ],
    "20": [
        "Prague",
        14.25,
        50.04
    ],
    "21": [
        "Rome",
        12.29,
        41.53
    ],
    "22": [
        "Stockholm",
        18.03,
        59.19
    ],
    "23": [
        "Strasbourg",
        7.45,
        48.35
    ],
    "24": [
        "Vienna",
        16.21,
        48.12
    ],
    "25": [
        "Warsaw",
        20.59,
        52.14
    ],
    "26": [
        "Zagreb",
        15.57,
        45.48
    ],
    "27": [
        "Zurich",
        8.32,
        47.22
    ],
    "28": [
        NaN,
        NaN,
        NaN
    ]
}